libkget/__init__.py
libkget/libkget.py
libkget-0.1.1.dist-info/METADATA
libkget-0.1.1.dist-info/WHEEL
libkget-0.1.1.dist-info/top_level.txt
libkget-0.1.1.dist-info/RECORD
